{
  "specMeta": {
    "specName": "GTRS",
    "specVersion": "1.0.0",
    "compatibleVersion": "1.0.0"
  },
  "themeInfo": {
    "themeId": "bubbleShooter_theme_default",
    "ownerType": "GAME",
    "ownerId": 0,
    "themeName": "泡泡射手",
    "isDefault": true,
    "gameId": "bubbleShooter",
    "description": "kids-game-simple bubbleShooter 默认 GTRS"
  },
  "globalStyle": {
    "primaryColor": "#4ECDC4",
    "secondaryColor": "#FFD93D",
    "bgColor": "#0f0c29",
    "textColor": "#FFFFFF",
    "fontFamily": "Arial, sans-serif"
  },
  "resources": {
    "images": {
      "login": {},
      "scene": {
        "background_dark": { "src": "#24243e", "type": "png", "alias": "背景底" },
        "bg_grad_mid": { "src": "#302b63", "type": "png", "alias": "背景中层" },
        "hud_bg": { "src": "rgba(15,25,45,0.85)", "type": "png", "alias": "HUD" },
        "accent": { "src": "#FFD700", "type": "png", "alias": "高亮" },
        "danger": { "src": "#FF4444", "type": "png", "alias": "危险" },
        "game_palette": {
          "src": "[\"#FF6B6B\",\"#FFD93D\",\"#6BCB77\",\"#4ECDC4\",\"#4D96FF\",\"#FF69B4\"]",
          "type": "png",
          "alias": "泡泡色板"
        }
      },
      "ui": {},
      "icon": {},
      "effect": {}
    },
    "audio": { "bgm": {}, "effect": {}, "voice": {} },
    "video": {}
  }
}
