{
  "$comment": "GTRS v1.0.0 游戏主题资源规范模板。此文件是主题开发的基础模板，包含所有必填字段和资源结构定义。使用方法：1. 复制此文件到游戏主题目录；2. 重命名为 GTRS.json；3. 根据游戏需求在 resources 中定义所需的资源 key；4. 放入实际资源文件。",
  "specMeta": {
    "specName": "GTRS",
    "specVersion": "1.0.0",
    "compatibleVersion": "1.0.0"
  },
  "globalStyle": {
    "bgColor": "#1a1a2e",
    "borderRadius": "8px",
    "fontFamily": "Arial, sans-serif",
    "primaryColor": "#4ade80",
    "secondaryColor": "#22c55e",
    "textColor": "#ffffff",
    "textSecondary": "#9ca3af",
    "accentColor": "#fbbf24",
    "errorColor": "#ef4444",
    "successColor": "#22c55e"
  },
  "resources": {
    "audio": {
      "bgm": {},
      "effect": {},
      "voice": {}
    },
    "images": {
      "scene": {},
      "effect": {},
      "icon": {},
      "ui": {},
      "login": {}
    },
    "video": {}
  }
}
